hckrnews/__init__.py
hckrnews/api.py
hckrnews/app.py
hckrnews/scraper.py
hckrnews/ui_utils.py
hckrnews/utils.py
hckrnews-0.1.1.dist-info/licenses/LICENSE.md
hckrnews-0.1.1.dist-info/METADATA
hckrnews-0.1.1.dist-info/WHEEL
hckrnews-0.1.1.dist-info/entry_points.txt
hckrnews-0.1.1.dist-info/top_level.txt
hckrnews-0.1.1.dist-info/RECORD
