Metadata-Version: 2.4
Name: hckrnews
Version: 0.1.1
Summary: Command line tool to display HN top stories
Requires-Python: >=3.13
License-File: LICENSE.md
Requires-Dist: requests>=2.32.3
Requires-Dist: rich>=14.0.0
Requires-Dist: textual>=3.2.0
Requires-Dist: beautifulsoup4>=4.13.4
Requires-Dist: pytz>=2025.2
Dynamic: license-file
